reusingintent/__init__.py
reusingintent/inference_core/__init__.py
reusingintent/inference_core/algorithms/dbscan.py
reusingintent/inference_core/algorithms/kmeans.py
reusingintent/inference_core/algorithms/linear_regression.py
reusingintent/inference_core/algorithms/range.py
reusingintent/inference_core/algorithms/skyline_algorithm.py
reusingintent/inference_core/core.py
reusingintent/inference_core/filter.py
reusingintent/inference_core/prediction.py
reusingintent/inference_core/prediction_stats.py
reusingintent/inference_core/rankings.py
reusingintent/inference_core/reapply/__init__.py
reusingintent/inference_core/reapply/compare.py
reusingintent/inference_core/reapply/data_structures/add_plot_interaction.py
reusingintent/inference_core/reapply/data_structures/apply_results.py
reusingintent/inference_core/reapply/data_structures/base_interaction.py
reusingintent/inference_core/reapply/data_structures/brush.py
reusingintent/inference_core/reapply/data_structures/brush_interaction.py
reusingintent/inference_core/reapply/data_structures/filter_interaction.py
reusingintent/inference_core/reapply/data_structures/interactions.py
reusingintent/inference_core/reapply/data_structures/plot.py
reusingintent/inference_core/reapply/data_structures/point_selection_interaction.py
reusingintent/inference_core/reapply/data_structures/select_prediction_interaction.py
reusingintent/inference_core/reapply/data_structures/types.py
reusingintent/inference_core/reapply/reapply.py
reusingintent/inference_core/reapply/reapply_algorithms/algorithm_picker.py
reusingintent/inference_core/reapply/reapply_algorithms/dbscan.py
reusingintent/inference_core/reapply/reapply_algorithms/kmeans.py
reusingintent/inference_core/reapply/reapply_algorithms/skyline.py
reusingintent/inference_core/utils.py
reusingintent/server/celery/init.py
reusingintent/server/celery/tasks.py
reusingintent/server/celery/utils.py
reusingintent/server/database/get_predictions.py
reusingintent-0.1.1.dist-info/WHEEL
reusingintent-0.1.1.dist-info/METADATA
reusingintent-0.1.1.dist-info/RECORD
